{
    "post_to_answer_found": true,
    "link_to_post_to_answer": "https://www.quora.com/What-was-the-last-time-someone-really-understand-your-feelings-and-how-does-it-feel",
    "content_of_post_to_answer": "What was the last time someone really understand your feelings and how does it feel?",
    "answer_generated": true,
    "answer": "Being truly understood is often less about someone having the perfect words and more about feeling that you do not have to defend or explain your experience. Many people listen to respond, fix, or compare. Rarely does someone simply stay with another person's reality without trying to change it. The surprising part is that feeling understood does not remove the problem; it removes the loneliness of carrying it alone."
}