{
    "post_to_answer_found": true,
    "link_to_post_to_answer": "https://www.quora.com/Who-has-the-problem-of-overthinking",
    "content_of_post_to_answer": "Who has the problem of overthinking?",
    "answer_generated": true,
    "answer": "Almost everyone overthinks sometimes, but the real difference is what happens next. Productive thinking ends with a decision; overthinking keeps trying to eliminate every uncertainty before acting. The irony is that more analysis often creates more doubt, because every answer reveals another question. At some point, clarity comes from action, not another round of thinking."
}