{
    "post_to_answer_found": true,
    "link_to_post_to_answer": "https://www.quora.com/Is-laziness-part-of-our-unconscious-mind",
    "content_of_post_to_answer": "Is laziness part of our unconscious mind?",
    "answer_generated": true,
    "answer": "Laziness is often not a command from the unconscious mind saying “do nothing”; it can be a signal that the brain is avoiding a perceived cost, uncertainty, boredom, or lack of meaning. What we call laziness may sometimes be a conflict between conscious goals and unconscious priorities. The interesting question is not “Why am I lazy?” but “What is my mind protecting me from by avoiding this action?”"
}